ButtonRequest/__init__.py
ButtonRequest/APIv1/Client.py
ButtonRequest/APIv1/__init__.py
ButtonRequest/APIv1/APIService/DShare.py
ButtonRequest/APIv1/APIService/DeviceList.py
ButtonRequest/APIv1/APIService/Message.py
ButtonRequest/APIv1/APIService/MobileAccess.py
ButtonRequest/APIv1/APIService/__init__.py
ButtonRequest/APIv1/CommonFunction/FilterData.py
ButtonRequest/APIv1/CommonFunction/__init__.py
ButtonRequest_APIv1-1.0.2.dist-info/METADATA
ButtonRequest_APIv1-1.0.2.dist-info/WHEEL
ButtonRequest_APIv1-1.0.2.dist-info/top_level.txt
ButtonRequest_APIv1-1.0.2.dist-info/RECORD
