Metadata-Version: 2.1
Name: ButtonRequest-APIv1
Version: 1.0.2
Summary: Button Request API v1 for Python
Home-page: 
Author: Yau Ming Leung
Author-email: ymleung918@gmail.com
License: MIT
Requires-Python: >=3.6
Requires-Dist: requests (==2.27.1)
Requires-Dist: urllib3
Requires-Dist: jsons
